atomize/__init__.py
atomize/__main__.py
atomize/codeeditor.py
atomize/config.ini
atomize/device_modules/Agilent_53131a.py
atomize/device_modules/Agilent_53181a.py
atomize/device_modules/Agilent_5343a.py
atomize/device_modules/BH_15.py
atomize/device_modules/CPWplus_150.py
atomize/device_modules/Cryomagnetics_4G.py
atomize/device_modules/Cryomagnetics_LM510.py
atomize/device_modules/Cryomech_CPA1110.py
atomize/device_modules/ECC_15K.py
atomize/device_modules/ER_031M.py
atomize/device_modules/ITC_503.py
atomize/device_modules/ITC_FC.py
atomize/device_modules/IVG_1_1.py
atomize/device_modules/Insys_FPGA.py
atomize/device_modules/Keysight_2000_Xseries.py
atomize/device_modules/Keysight_3000_Xseries.py
atomize/device_modules/Keysight_4000_Xseries.py
atomize/device_modules/Keysight_53230a.py
atomize/device_modules/L_card_L502.py
atomize/device_modules/Lakeshore_325.py
atomize/device_modules/Lakeshore_331.py
atomize/device_modules/Lakeshore_332.py
atomize/device_modules/Lakeshore_335.py
atomize/device_modules/Lakeshore_336.py
atomize/device_modules/Lakeshore_340.py
atomize/device_modules/Lakeshore_455_DSP.py
atomize/device_modules/Micran_Q_band_MW_bridge.py
atomize/device_modules/Micran_X_band_MW_bridge.py
atomize/device_modules/Micran_X_band_MW_bridge_v2.py
atomize/device_modules/Owen_MK110_220_4DN_4R.py
atomize/device_modules/PB_ESR_500_pro.py
atomize/device_modules/PB_Micran.py
atomize/device_modules/Planar_C2220.py
atomize/device_modules/Rigol_DP800_Series.py
atomize/device_modules/Rodos_10N.py
atomize/device_modules/SR_810.py
atomize/device_modules/SR_830.py
atomize/device_modules/SR_844.py
atomize/device_modules/SR_850.py
atomize/device_modules/SR_860.py
atomize/device_modules/SR_865a.py
atomize/device_modules/SR_DC205.py
atomize/device_modules/SR_DG535.py
atomize/device_modules/SR_PS300_Series.py
atomize/device_modules/SR_PTC_10.py
atomize/device_modules/Scientific_Instruments_SCM10.py
atomize/device_modules/Sibir_1.py
atomize/device_modules/Spectrum_M4I_2211_X8.py
atomize_py-0.2.6.dist-info/METADATA
atomize_py-0.2.6.dist-info/WHEEL
atomize_py-0.2.6.dist-info/entry_points.txt
atomize_py-0.2.6.dist-info/licenses/license.md
atomize_py-0.2.6.dist-info/RECORD
