Metadata-Version: 2.4
Name: atomize-py
Version: 0.2.6
Summary: A modular software for working with scientific devices and combining them into unified multifunctional setup
Project-URL: Homepage, https://github.com/Anatoly1010/Atomize
Project-URL: Issues, https://github.com/Anatoly1010/Atomize/issues
Project-URL: Documentation, https://github.com/Anatoly1010/Atomize/tree/master/atomize/documentation
Author: Atomize Developers
License-Expression: MIT
License-File: license.md
Keywords: automation,experimental script,graph,industrial instruments,instrument control,measurement,scientific instruments
Classifier: Intended Audience :: Science/Research
Classifier: Operating System :: MacOS
Classifier: Operating System :: Microsoft :: Windows
Classifier: Operating System :: POSIX
Classifier: Operating System :: Unix
Classifier: Programming Language :: Python :: 3
Classifier: Topic :: Scientific/Engineering
Requires-Python: >=3.10
Requires-Dist: numpy>=1.25
Requires-Dist: platformdirs>=4.5
Requires-Dist: pyqt6>=6.2
Requires-Dist: pyqtgraph>=0.12
Requires-Dist: pyvisa-py>=0.5
Requires-Dist: pyvisa>=1.11
Provides-Extra: bots
Requires-Dist: pytelegrambotapi>=4.15; extra == 'bots'
Provides-Extra: gui
Requires-Dist: tkinter>=8.6; extra == 'gui'
Provides-Extra: math
Requires-Dist: scipy>=1.15; extra == 'math'
Provides-Extra: modbus
Requires-Dist: minimalmodbus>=1.0; extra == 'modbus'
Provides-Extra: serial
Requires-Dist: pyserial>=3.5; extra == 'serial'
